path_sync/__init__.py
path_sync/__main__.py
path_sync/config.py
path_sync/copy.py
path_sync/sections.py
path_sync/_internal/__init__.py
path_sync/_internal/cmd_boot.py
path_sync/_internal/cmd_copy.py
path_sync/_internal/cmd_validate.py
path_sync/_internal/file_utils.py
path_sync/_internal/git_ops.py
path_sync/_internal/header.py
path_sync/_internal/models.py
path_sync/_internal/typer_app.py
path_sync/_internal/validation.py
path_sync/_internal/yaml_utils.py
path_sync-0.3.3.dist-info/METADATA
path_sync-0.3.3.dist-info/WHEEL
path_sync-0.3.3.dist-info/entry_points.txt
path_sync-0.3.3.dist-info/licenses/LICENSE
path_sync-0.3.3.dist-info/RECORD
