Metadata-Version: 2.4
Name: path-sync
Version: 0.3.3
Summary: Sync files from a source repo to multiple destination repos
Author-email: EspenAlbert <espen.albert1@gmail.com>
License-Expression: MIT
License-File: LICENSE
Keywords: cli,repository,sync,template
Classifier: Development Status :: 4 - Beta
Classifier: Programming Language :: Python :: 3.13
Requires-Python: >=3.13
Requires-Dist: gitpython>=3.1.0
Requires-Dist: pydantic>=2.0
Requires-Dist: pyyaml>=6.0
Requires-Dist: typer>=0.16.0
Requires-Dist: zero-3rdparty>=0.101.1
